ontouml_py/__init__.py
ontouml_py/classes/__init__.py
ontouml_py/classes/abstract_classes/__init__.py
ontouml_py/classes/abstract_classes/classifier.py
ontouml_py/classes/abstract_classes/decoratable.py
ontouml_py/classes/abstract_classes/modelelement.py
ontouml_py/classes/abstract_classes/namedelement.py
ontouml_py/classes/abstract_classes/ontoumlelement.py
ontouml_py/classes/abstract_classes/packageable.py
ontouml_py/classes/abstract_classes/projectelement.py
ontouml_py/classes/abstract_classes/relation.py
ontouml_py/classes/concrete_classes/__init__.py
ontouml_py/classes/concrete_classes/anchor.py
ontouml_py/classes/concrete_classes/binaryrelation.py
ontouml_py/classes/concrete_classes/class_py.py
ontouml_py/classes/concrete_classes/generalization.py
ontouml_py/classes/concrete_classes/generalizationset.py
ontouml_py/classes/concrete_classes/literal.py
ontouml_py/classes/concrete_classes/naryrelation.py
ontouml_py/classes/concrete_classes/note.py
ontouml_py/classes/concrete_classes/package.py
ontouml_py/classes/concrete_classes/project.py
ontouml_py/classes/concrete_classes/property.py
ontouml_py/classes/datatypes/__init__.py
ontouml_py/classes/datatypes/cardinality.py
ontouml_py/classes/enumerations/__init__.py
ontouml_py/classes/enumerations/aggregationkind.py
ontouml_py/classes/enumerations/classstereotype.py
ontouml_py/classes/enumerations/ontologicalnature.py
ontouml_py/classes/enumerations/ontologyrepresentationstyle.py
ontouml_py/classes/enumerations/ontouml_enum.py
ontouml_py/classes/enumerations/propertystereotype.py
ontouml_py/classes/enumerations/relationstereotype.py
ontouml_py/classes/utils/__init__.py
ontouml_py/classes/utils/error_message.py
ontouml_py/classes/utils/nonemptyset.py
ontouml_py/py.typed
ontouml_py-0.2.0.dist-info/METADATA
ontouml_py-0.2.0.dist-info/WHEEL
ontouml_py-0.2.0.dist-info/RECORD
