Metadata-Version: 2.1
Name: ontouml-py
Version: 0.2.0
Summary: OntoUML Python Library
Home-page: https://w3id.org/ontouml/ontouml-py
License: Apache-2.0
Keywords: conceptual-model,ontology,ontology-driven-development,ontouml,ontouml-metamodel,unified-foundational-ontology
Author: Pedro Paulo F. Barcelos
Author-email: p.p.favatobarcelos@utwente.nl
Requires-Python: >=3.09,<4.0
Classifier: License :: OSI Approved :: Apache Software License
Classifier: Programming Language :: Python :: 3
Classifier: Programming Language :: Python :: 3.9
Classifier: Programming Language :: Python :: 3.10
Classifier: Programming Language :: Python :: 3.11
Classifier: Programming Language :: Python :: 3.12
Requires-Dist: langstring (>=1.0.0,<2.0.0)
Requires-Dist: pydantic (>=2.5.2,<3.0.0)
Project-URL: Documentation, https://w3id.org/ontouml/ontouml-py/docs
Project-URL: PyPi Project, https://pypi.org/project/ontouml-py/
Project-URL: Repository, https://w3id.org/ontouml/ontouml-py
